vintools/__init__.py
vintools/_data/__init__.py
vintools/_plotting/__init__.py
vintools/_plotting/_annotate_legend.py
vintools/_plotting/_get_default_figure_height_width.py
vintools/_plotting/_histogram_2d_component_plot.py
vintools/_plotting/_modify_ax_spines.py
vintools/_plotting/_plot_correlation_heatmap.py
vintools/_plotting/_set_minimal_ticks.py
vintools/_plotting/color_palettes.py
vintools/_plotting/fig_presets.py
vintools/_plotting/make_data_gif.py
vintools/_plotting/share_seq_df_generation.py
vintools/_single_cell/__init__.py
vintools/_single_cell/_general_formatting_tools.py
vintools/_single_cell/_parse_counts.py
vintools/_single_cell/_sc_preprocessing.py
vintools/_testing_and_development/__init__.py
vintools/_testing_and_development/_dev_libraries.py
vintools/_testing_and_development/_handle_kwargs.py
vintools/_tools/__init__.py
vintools/_utilities/__init__.py
vintools-0.0.55.dist-info/LICENSE
vintools-0.0.55.dist-info/METADATA
vintools-0.0.55.dist-info/WHEEL
vintools-0.0.55.dist-info/top_level.txt
vintools-0.0.55.dist-info/RECORD
