Metadata-Version: 2.1
Name: vintools
Version: 0.0.55
Summary: vintools - Michael Vinyard's utilities.
Home-page: https://github.com/mvinyard/vintools
Author: Michael E. Vinyard - Harvard University - Massachussetts General Hospital - Broad Institute of MIT and Harvard
Author-email: mvinyard@broadinstitute.org
License: MIT
Platform: UNKNOWN
Classifier: Development Status :: 2 - Pre-Alpha
Classifier: Programming Language :: Python :: 3.8
Classifier: Intended Audience :: Science/Research
Classifier: Topic :: Scientific/Engineering :: Bio-Informatics
Requires-Python: >3.8.0
License-File: LICENSE
Requires-Dist: matplotlib (>=3.4)
Requires-Dist: anndata (>=0.7.1)
Requires-Dist: scanpy (>=1.4.3)
Requires-Dist: scprep (>=1.1.0)
Requires-Dist: torch (>=1.1.0)
Requires-Dist: numpy (>=1.19.2)
Requires-Dist: pandas (>=1.1.2)
Requires-Dist: pysam (>=0.16.0)
Requires-Dist: torchdiffeq (>=0.2.1)
Requires-Dist: harmony-pytorch (>=0.1.6)
Requires-Dist: psutil (>=5.8.0)
Requires-Dist: biopython (>=1.79)
